logictool/optimap.py
logictool/truthy.py
logictool-0.1.0.dist-info/METADATA
logictool-0.1.0.dist-info/WHEEL
logictool-0.1.0.dist-info/entry_points.txt
logictool-0.1.0.dist-info/top_level.txt
logictool-0.1.0.dist-info/RECORD
